{
  "ticker": "GOOGL",
  "company_name": "Alphabet Inc.",
  "sector": "Communication Services",
  "industry": "Internet Content & Information",
  "market_cap": 2985129934848,
  "current_price": 244.89999389648438,
  "price_52w_high": 256.0,
  "price_52w_low": 140.2346601251265,
  "avg_volume": 34198702.0,
  "pe_ratio": 26.305046,
  "forward_pe": 27.332588,
  "peg_ratio": null,
  "price_to_book": 8.167962,
  "debt_to_equity": 11.481,
  "revenue": 371399000064,
  "revenue_growth": 0.138,
  "profit_margin": 0.31118,
  "operating_margin": 0.32429,
  "return_on_equity": 0.34829,
  "return_on_assets": 0.16792,
  "returns_1m": 0.2297763774213443,
  "returns_3m": 0.45673277213662516,
  "returns_6m": 0.29546772595768545,
  "returns_1y": null,
  "volatility": 0.3222761517623067,
  "beta": 1.0,
  "employees": 187103,
  "data_collection_date": "2025-10-02T08:41:58.989072"
}